ppaudio/__init__.py
ppaudio/api.py
ppaudio/tester.py
ppaudio/trainer.py
ppaudio/config/__init__.py
ppaudio/config/config_parser.py
ppaudio/configs/motor.yaml
ppaudio/core/__init__.py
ppaudio/core/audio.py
ppaudio/core/dataset.py
ppaudio/core/features.py
ppaudio/core/label.py
ppaudio/core/trainer.py
ppaudio/models/__init__.py
ppaudio/models/cnn.py
ppaudio/models/lstm.py
ppaudio/models/model_factory.py
ppaudio/utils/__init__.py
ppaudio/utils/audio_utils.py
ppaudio/utils/logger.py
ppaudio/utils/visualization.py
ppaudio-0.1.2.dist-info/LICENSE
ppaudio-0.1.2.dist-info/METADATA
ppaudio-0.1.2.dist-info/WHEEL
ppaudio-0.1.2.dist-info/entry_points.txt
ppaudio-0.1.2.dist-info/top_level.txt
ppaudio-0.1.2.dist-info/RECORD
