Metadata-Version: 2.1
Name: ppaudio
Version: 0.1.2
Summary: An audio classification toolkit based on PaddlePaddle for detecting abnormal sounds
Home-page: https://github.com/kid/ppaudio
Author: Kid
Author-email: kid@example.com
License: UNKNOWN
Keywords: audio,classification,deep learning,paddlepaddle,sound detection
Platform: UNKNOWN
Classifier: Development Status :: 4 - Beta
Classifier: Intended Audience :: Developers
Classifier: Intended Audience :: Science/Research
Classifier: License :: OSI Approved :: MIT License
Classifier: Operating System :: OS Independent
Classifier: Programming Language :: Python :: 3
Classifier: Programming Language :: Python :: 3.7
Classifier: Programming Language :: Python :: 3.8
Classifier: Programming Language :: Python :: 3.9
Classifier: Topic :: Scientific/Engineering :: Artificial Intelligence
Classifier: Topic :: Software Development :: Libraries :: Python Modules
Classifier: Topic :: Multimedia :: Sound/Audio :: Analysis
Requires-Python: >=3.7
License-File: LICENSE
Requires-Dist: paddlepaddle (>=2.6.1)
Requires-Dist: paddleaudio (>=1.0.1)
Requires-Dist: paddlespeech (>=1.4.1)
Requires-Dist: numpy (>=1.19.0)
Requires-Dist: matplotlib (>=3.3.0)
Requires-Dist: scipy (>=1.7.0)
Requires-Dist: pyyaml (>=5.4.0)
Requires-Dist: librosa (>=0.10.0)
